LbAPLocal/__init__.py
LbAPLocal/cli.py
LbAPLocal/log_parsing.py
LbAPLocal/testing.py
LbAPLocal/utils.py
lbaplocal-0.8.0.dist-info/licenses/LICENSE
lbaplocal-0.8.0.dist-info/METADATA
lbaplocal-0.8.0.dist-info/WHEEL
lbaplocal-0.8.0.dist-info/entry_points.txt
lbaplocal-0.8.0.dist-info/top_level.txt
lbaplocal-0.8.0.dist-info/RECORD
