Metadata-Version: 2.4
Name: LbAPLocal
Version: 0.8.0
Summary: Tool to locally run tests for AnalysisProductions
Author: LHCb
Project-URL: Homepage, https://gitlab.cern.ch/lhcb-dpa/analysis-productions/lbaplocal
Project-URL: Bug Reports, https://gitlab.cern.ch/lhcb-dpa/analysis-productions/lbaplocal/-/issues
Project-URL: Source, https://gitlab.cern.ch/lhcb-dpa/analysis-productions/lbaplocal
Keywords: LHCb AnalysisProductions DIRAC
Classifier: Development Status :: 4 - Beta
Classifier: License :: OSI Approved :: GNU General Public License v3 or later (GPLv3+)
Classifier: Programming Language :: Python :: 3
Requires-Python: >=3.12
License-File: LICENSE
Requires-Dist: LbAPCommon>=0.13.5
Requires-Dist: LbDiracWrappers
Requires-Dist: LbEnv
Requires-Dist: LbProdRun~=1.3
Requires-Dist: apd>=0.6.0
Requires-Dist: click
Requires-Dist: consolemd
Requires-Dist: mplhep
Requires-Dist: requests
Requires-Dist: setuptools
Provides-Extra: testing
Requires-Dist: pytest; extra == "testing"
Requires-Dist: pytest-cov; extra == "testing"
Requires-Dist: pytest-mock; extra == "testing"
Requires-Dist: pytest-recording; extra == "testing"
Requires-Dist: pytest-timeout; extra == "testing"
Dynamic: license-file
